insights-plotrisk/__init__.py
insights-plotrisk/api_client.py
insights-plotrisk/configuration.py
insights-plotrisk/rest.py
insights-plotrisk/api/__init__.py
insights-plotrisk/api/crops_controller_api.py
insights-plotrisk/api/custom_boundary_controller_api.py
insights-plotrisk/api/entity_audit_collection_controller_api.py
insights-plotrisk/api/generic_o_data_controller_api.py
insights-plotrisk/api/weather_data_controller_api.py
insights-plotrisk/api/yield_data_controller_api.py
insights-plotrisk/models/__init__.py
insights-plotrisk/models/boundary_request.py
insights-plotrisk/models/boundary_response.py
insights-plotrisk/models/crop_detail.py
insights-plotrisk/models/crop_request.py
insights-plotrisk/models/crop_response.py
insights-plotrisk/models/entity_audit_collection_request.py
insights-plotrisk/models/entity_audit_collection_response.py
insights-plotrisk/models/feature_collection_req.py
insights-plotrisk/models/feature_collection_res.py
insights-plotrisk/models/feature_req.py
insights-plotrisk/models/feature_res.py
insights-plotrisk/models/gdd.py
insights-plotrisk/models/geometry.py
insights-plotrisk/models/geometry_collection.py
insights-plotrisk/models/line_string.py
insights-plotrisk/models/multi_line_string.py
insights-plotrisk/models/multi_point.py
insights-plotrisk/models/multi_polygon.py
insights-plotrisk/models/point.py
insights-plotrisk/models/polygon.py
insights-plotrisk/models/weather.py
insights-plotrisk/models/weather_data_request.py
insights-plotrisk/models/weather_data_response.py
insights-plotrisk/models/yield_request.py
insights-plotrisk/models/yield_response.py
insights-plotrisk/models/yields_data.py
test/__init__.py
test/test_boundary_request.py
test/test_boundary_response.py
test/test_crop_detail.py
test/test_crop_request.py
test/test_crop_response.py
test/test_crops_controller_api.py
test/test_custom_boundary_controller_api.py
test/test_entity_audit_collection_controller_api.py
test/test_entity_audit_collection_request.py
insights_plotrisk-0.0.1.dist-info/METADATA
insights_plotrisk-0.0.1.dist-info/WHEEL
insights_plotrisk-0.0.1.dist-info/top_level.txt
insights_plotrisk-0.0.1.dist-info/RECORD
