Metadata-Version: 2.1
Name: insights-plotrisk
Version: 0.0.1
Summary: InsightsServices-Dev-QA
Home-page: 
Author-email: 
Keywords: Swagger,InsightsServices-Dev-QA
Requires-Dist: certifi (>=2017.4.17)
Requires-Dist: python-dateutil (>=2.1)
Requires-Dist: six (>=1.10)
Requires-Dist: urllib3 (>=1.23)
